tseqmock/__init__.py
tseqmock/core.py
tseqmock/exception.py
tseqmock/version.py
tseqmock/distribution/__init__.py
tseqmock/distribution/base.py
tseqmock/distribution/config.py
tseqmock/distribution/type/__init__.py
tseqmock/distribution/type/normal/__init__.py
tseqmock/distribution/type/normal/distribution.py
tseqmock/distribution/type/normal/settings.py
tseqmock/distribution/type/uniform/__init__.py
tseqmock/distribution/type/uniform/distribution.py
tseqmock/distribution/type/uniform/settings.py
tseqmock/generator/__init__.py
tseqmock/generator/config.py
tseqmock/generator/base/__init__.py
tseqmock/generator/base/generator.py
tseqmock/generator/base/granularity.py
tseqmock/generator/base/profile.py
tseqmock/generator/base/settings.py
tseqmock/generator/base/utils.py
tseqmock/generator/type/__init__.py
tseqmock/generator/type/event/__init__.py
tseqmock/generator/type/event/generator.py
tseqmock/generator/type/event/settings.py
tseqmock/generator/type/event/time_design.py
tseqmock/generator/type/interval/__init__.py
tseqmock/generator/type/interval/generator.py
tseqmock/generator/type/interval/settings.py
tseqmock/generator/type/interval/time_design.py
tseqmock/generator/type/state/__init__.py
tseqmock/generator/type/state/generator.py
tseqmock/generator/type/state/settings.py
tseqmock/generator/type/state/time_design.py
tseqmock/method/__init__.py
tseqmock/method/base.py
tseqmock/method/config.py
tseqmock/method/type/__init__.py
tseqmock/method/type/random/__init__.py
tseqmock/method/type/random/method.py
tseqmock/method/type/random/settings.py
tseqmock/time_strategy/__init__.py
tseqmock/time_strategy/base.py
tseqmock/time_strategy/type/__init__.py
tseqmock/time_strategy/type/fixed/__init__.py
tseqmock/time_strategy/type/fixed/settings.py
tseqmock/time_strategy/type/fixed/strategy.py
tseqmock/time_strategy/type/sequence_specific/__init__.py
tseqmock/time_strategy/type/sequence_specific/settings.py
tseqmock/time_strategy/type/sequence_specific/strategy.py
tseqmock-2.0.1.dist-info/METADATA
tseqmock-2.0.1.dist-info/WHEEL
tseqmock-2.0.1.dist-info/licenses/LICENSE.txt
tseqmock-2.0.1.dist-info/RECORD
