Metadata-Version: 2.4
Name: TSeqMock
Version: 2.0.1
Summary: A library for temporal sequence simulation.
Project-URL: Homepage, https://gitlab.inria.fr/tanat/core/tseqmock
Project-URL: Source, https://gitlab.inria.fr/tanat/core/tseqmock.git
Project-URL: Documentation, https://tanat.gitlabpages.inria.fr/tseqmock/
Project-URL: Issues, https://gitlab.inria.fr/tanat/core/tseqmock/-/issues
Author: Gagnieu Thomas, Gueye Ndeye, Riou Baptiste, Sebai Imene
Author-email: Arnaud Duvermy <arnaud.duvermy@inria.fr>, Thomas Guyet <thomas.guyet@inria.fr>
Maintainer-email: Thomas Guyet <thomas.guyet@inria.fr>
License: MIT License
License-File: LICENSE.txt
Classifier: License :: OSI Approved :: MIT License
Classifier: Operating System :: OS Independent
Classifier: Programming Language :: Python :: 3
Requires-Python: >=3.7
Requires-Dist: numpy
Requires-Dist: pandas
Requires-Dist: pypassist
Requires-Dist: scipy
Provides-Extra: test
Requires-Dist: pytest; extra == 'test'
Requires-Dist: syrupy; extra == 'test'
